jdEolConverter/Icon.svg
jdEolConverter/MainWindow.ui
jdEolConverter/__init__.py
jdEolConverter/__main__.py
jdEolConverter/translations/jdEolConverter_de.qm
jdEolConverter/translations/jdEolConverter_nl.qm
jdEolConverter-1.2.dist-info/LICENSE
jdEolConverter-1.2.dist-info/METADATA
jdEolConverter-1.2.dist-info/WHEEL
jdEolConverter-1.2.dist-info/entry_points.txt
jdEolConverter-1.2.dist-info/top_level.txt
jdEolConverter-1.2.dist-info/RECORD
